.gitignore
HISTORY
README
setup.py
cmsmenu_redirect/__init__.py
cmsmenu_redirect/menu.py
cmsmenu_redirect.egg-info/PKG-INFO
cmsmenu_redirect.egg-info/SOURCES.txt
cmsmenu_redirect.egg-info/dependency_links.txt
cmsmenu_redirect.egg-info/not-zip-safe
cmsmenu_redirect.egg-info/requires.txt
cmsmenu_redirect.egg-info/top_level.txt