Metadata-Version: 1.0
Name: cmsmenu-redirect
Version: 0.1
Summary: Django CMS Menu Plugin for Django Contrib Redirects
Home-page: https://github.com/benliles/cmsmenu-redirect
Author: Benjamin Liles
Author-email: ben@ltwebdev.com
License: UNKNOWN
Keywords: django cms plugin menu
Platform: UNKNOWN
Classifier: Framework :: Django
Classifier: Development Status :: 4 - Beta
Classifier: Programming Language :: Python
Classifier: Framework :: Django
Classifier: Topic :: Multimedia :: Graphics
Classifier: Topic :: Software Development :: Libraries :: Python Modules
